MANIFEST.in
README.org
setup.py
flask_tlsauth/__init__.py
flask_tlsauth.egg-info/PKG-INFO
flask_tlsauth.egg-info/SOURCES.txt
flask_tlsauth.egg-info/dependency_links.txt
flask_tlsauth.egg-info/requires.txt
flask_tlsauth.egg-info/top_level.txt