Metadata-Version: 1.1
Name: flask-tlsauth
Version: 0.1.3
Summary: Flask extension implementing TLS Authentication - simple client certificate CA inclusive
Home-page: http://packages.python.org/flask_tlsauth
Author: Stefan Marsiske
Author-email: s@ctrlc.hu
License: BSD
Keywords: flask crypto authentication TLS certificate x509 CA
Platform: UNKNOWN
Classifier: Development Status :: 4 - Beta
Classifier: License :: OSI Approved :: BSD License
Classifier: Topic :: Security :: Cryptography
Classifier: Environment :: Web Environment
